smartpasslib/__init__.py
smartpasslib/factories/__init__.py
smartpasslib/factories/smart_password_factory.py
smartpasslib/generators/__init__.py
smartpasslib/generators/base.py
smartpasslib/generators/code.py
smartpasslib/generators/hash.py
smartpasslib/generators/key.py
smartpasslib/generators/smart.py
smartpasslib/generators/strong.py
smartpasslib/generators/urandom.py
smartpasslib/managers/__init__.py
smartpasslib/managers/smart_password_manager.py
smartpasslib/masters/__init__.py
smartpasslib/masters/smart_password_master.py
smartpasslib/smart_passwords/__init__.py
smartpasslib/smart_passwords/smart_password.py
smartpasslib/utils/__init__.py
smartpasslib/utils/decorators.py
smartpasslib-2.1.1.dist-info/licenses/LICENSE
tests/__init__.py
tests/conftest.py
tests/test_factories/__init__.py
tests/test_factories/test_factory.py
tests/test_generators/__init__.py
tests/test_generators/test_base.py
tests/test_generators/test_code.py
tests/test_generators/test_hash.py
tests/test_generators/test_key.py
tests/test_generators/test_smart.py
tests/test_generators/test_strong.py
tests/test_generators/test_urandom.py
tests/test_managers/__init__.py
tests/test_managers/test_manager.py
tests/test_masters/__init__.py
tests/test_masters/test_master.py
tests/test_passwords/__init__.py
tests/test_passwords/test_password.py
tests/test_utils/__init__.py
tests/test_utils/test_decorators.py
smartpasslib-2.1.1.dist-info/METADATA
smartpasslib-2.1.1.dist-info/WHEEL
smartpasslib-2.1.1.dist-info/top_level.txt
smartpasslib-2.1.1.dist-info/RECORD
