Metadata-Version: 2.4
Name: smartpasslib
Version: 2.1.1
Summary: Smart Passwords Library: Cryptographic password generation and management without storage. Generate passwords from secrets, verify knowledge without exposure, manage metadata securely.
Author-email: Alexander Suvorov <smartlegiondev@gmail.com>
License-Expression: BSD-3-Clause
Project-URL: Homepage, https://github.com/smartlegionlab/smartpasslib
Classifier: Programming Language :: Python :: 3
Classifier: Programming Language :: Python :: 3.7
Classifier: Programming Language :: Python :: 3.8
Classifier: Programming Language :: Python :: 3.9
Classifier: Programming Language :: Python :: 3.10
Classifier: Programming Language :: Python :: 3.11
Classifier: Programming Language :: Python :: 3.12
Classifier: Operating System :: OS Independent
Classifier: Topic :: Security
Requires-Python: >=3.6
License-File: LICENSE
Dynamic: license-file
